mengzhongjia/__init__.py
mengzhongjia-1.0.dist-info/METADATA
mengzhongjia-1.0.dist-info/WHEEL
mengzhongjia-1.0.dist-info/top_level.txt
mengzhongjia-1.0.dist-info/RECORD
