Metadata-Version: 2.1
Name: mengzhongjia
Version: 1.0
Summary: 这是第一个对外发布的模块，测试哦
Author: mzj
Author-email: mengzhongjia1113@163.com
